jaypeg/__init__.py
jaypeg/__main__.py
jaypeg/main.py
jaypeg-0.1.2.dist-info/entry_points.txt
jaypeg-0.1.2.dist-info/WHEEL
jaypeg-0.1.2.dist-info/METADATA
jaypeg-0.1.2.dist-info/RECORD
